LICENSE
MANIFEST.in
README.rst
setup.cfg
setup.py
CRISPResso/.DS_Store
CRISPResso/CRISPRessoCORE.py
CRISPResso/CRISPRessoCompareCORE.py
CRISPResso/CRISPRessoCountCORE.py
CRISPResso/CRISPRessoPooledCORE.py
CRISPResso/CRISPRessoPooledWGSCompareCORE.py
CRISPResso/CRISPRessoWGSCORE.py
CRISPResso/__init__.py
CRISPResso/__main__.py
CRISPResso.egg-info/PKG-INFO
CRISPResso.egg-info/SOURCES.txt
CRISPResso.egg-info/dependency_links.txt
CRISPResso.egg-info/entry_points.txt
CRISPResso.egg-info/requires.txt
CRISPResso.egg-info/top_level.txt
CRISPResso/data/.DS_Store
CRISPResso/data/NexteraPE-PE.fa
CRISPResso/data/TruSeq2-PE.fa
CRISPResso/data/TruSeq2-SE.fa
CRISPResso/data/TruSeq3-PE-2.fa
CRISPResso/data/TruSeq3-PE.fa
CRISPResso/data/TruSeq3-SE.fa
CRISPResso/data/trimmomatic-0.33.jar
dependencies/EMBOSS-6.5.7.tar.gz
dependencies/FLASH-1.2.11.tar.gz