Metadata-Version: 1.1
Name: CRISPResso
Version: 1.0.13
Summary: Software pipeline for the analysis of CRISPR-Cas9 genome editing outcomes from deep sequencing data
Home-page: http://github.com/lucapinello/CRISPResso
Author: Luca Pinello
Author-email: lpinello@jimmy.harvard.edu
License: UNKNOWN
Platform: UNKNOWN
Classifier: Development Status :: 4 - Beta
Classifier: Environment :: Console
Classifier: Intended Audience :: Developers
Classifier: Intended Audience :: Science/Research
Classifier: License :: OSI Approved :: BSD License
Classifier: Operating System :: MacOS :: MacOS X
Classifier: Operating System :: POSIX
Classifier: Topic :: Scientific/Engineering :: Bio-Informatics
Classifier: Programming Language :: Python
